csv_server/__init__.py
csv_server/app.py
csv_server/cli.py
csv_server/config.py
csv_server/exceptions.py
csv_server/query.py
csv_server/resources.py
csv_server/utils_csv_ids.py
csv_server/version.py
csv_server/storage/__init__.py
csv_server/storage/base.py
csv_server/storage/csv_store.py
csv_server/storage/sqlite_store.py
csv_server-0.1.2.dist-info/licenses/LICENSE
csv_server-0.1.2.dist-info/METADATA
csv_server-0.1.2.dist-info/WHEEL
csv_server-0.1.2.dist-info/entry_points.txt
csv_server-0.1.2.dist-info/top_level.txt
csv_server-0.1.2.dist-info/RECORD
