Metadata-Version: 2.4
Name: csv-server
Version: 0.1.2
Summary: A FastAPI-based REST API server for CSV files
Author-email: Rohit Nagotkar <rohitajaynagotkar@gmail.com>
License: MIT
Project-URL: Homepage, https://github.com/rxhxt/csv-server
Project-URL: Repository, https://github.com/rxhxt/csv-server
Project-URL: Issues, https://github.com/rxhxt/csv-server/issues
Keywords: csv,api,rest,fastapi,server
Classifier: Development Status :: 4 - Beta
Classifier: Intended Audience :: Developers
Classifier: License :: OSI Approved :: MIT License
Classifier: Operating System :: OS Independent
Classifier: Programming Language :: Python :: 3
Classifier: Programming Language :: Python :: 3.8
Classifier: Programming Language :: Python :: 3.9
Classifier: Programming Language :: Python :: 3.10
Classifier: Programming Language :: Python :: 3.11
Classifier: Programming Language :: Python :: 3.12
Requires-Python: >=3.8
License-File: LICENSE
Requires-Dist: fastapi>=0.68.0
Requires-Dist: uvicorn[standard]>=0.15.0
Requires-Dist: pyyaml>=5.4.0
Requires-Dist: portalocker>=2.0.0
Requires-Dist: click>=8.0.0
Requires-Dist: pydantic>=1.8.0
Provides-Extra: dev
Requires-Dist: pytest>=6.0; extra == "dev"
Requires-Dist: pytest-asyncio>=0.18.0; extra == "dev"
Requires-Dist: httpx>=0.23.0; extra == "dev"
Requires-Dist: black>=22.0.0; extra == "dev"
Requires-Dist: flake8>=4.0.0; extra == "dev"
Requires-Dist: mypy>=0.910; extra == "dev"
Requires-Dist: isort>=5.10.0; extra == "dev"
Requires-Dist: coverage>=6.0; extra == "dev"
Dynamic: license-file
